tests/__init__.py
vmf_tool/__init__.py
vmf_tool/brushes.py
vmf_tool/parser.py
vmf_tool/vector.py
vmf_tool/vmf.py
vmf_tool-0.1.0.dist-info/LICENSE
vmf_tool-0.1.0.dist-info/METADATA
vmf_tool-0.1.0.dist-info/WHEEL
vmf_tool-0.1.0.dist-info/top_level.txt
vmf_tool-0.1.0.dist-info/RECORD
